rasp_parser/__init__.py
rasp_parser/core.py
rasp_parser/exceptions.py
rasp_parser/models.py
rasp_parser/validation.py
rasp_parser-1.0.0.dist-info/licenses/LICENSE
rasp_parser-1.0.0.dist-info/METADATA
rasp_parser-1.0.0.dist-info/WHEEL
rasp_parser-1.0.0.dist-info/entry_points.txt
rasp_parser-1.0.0.dist-info/top_level.txt
rasp_parser-1.0.0.dist-info/RECORD
