Metadata-Version: 2.4
Name: rasp-parser
Version: 1.0.0
Summary: A Python library for parsing RASP rocket motor data files
Author-email: gituser12981u2 <squarer.human-0t@icloud.com>
Project-URL: Homepage, https://github.com/gituser12981u2/rasp-parser
Project-URL: Repository, https://github.com/gituser12981u2/rasp-parser
Project-URL: Documentation, https://rasp-parser.readthedocs.io
Project-URL: Bug Tracker, https://github.com/gituser12981u2/rasp-parser/issues
Keywords: rocket,motor,rasp,simulation,aerospace,propulsion
Classifier: Development Status :: 5 - Production/Stable
Classifier: Intended Audience :: Science/Research
Classifier: Topic :: Scientific/Engineering :: Physics
Classifier: License :: OSI Approved :: MIT License
Classifier: Programming Language :: Python :: 3
Classifier: Programming Language :: Python :: 3.8
Classifier: Programming Language :: Python :: 3.9
Classifier: Programming Language :: Python :: 3.10
Classifier: Programming Language :: Python :: 3.11
Classifier: Programming Language :: Python :: 3.12
Requires-Python: >=3.8
License-File: LICENSE
Provides-Extra: scipy
Requires-Dist: scipy>=1.7.0; extra == "scipy"
Provides-Extra: dev
Requires-Dist: pytest>=6.0; extra == "dev"
Requires-Dist: pytest-cov; extra == "dev"
Requires-Dist: black; extra == "dev"
Requires-Dist: flake8; extra == "dev"
Requires-Dist: mypy; extra == "dev"
Requires-Dist: twine; extra == "dev"
Requires-Dist: build; extra == "dev"
Provides-Extra: docs
Requires-Dist: sphinx; extra == "docs"
Requires-Dist: sphinx-rtd-theme; extra == "docs"
Requires-Dist: myst-parser; extra == "docs"
Dynamic: license-file
